xtcocotools/__init__.py
xtcocotools/_mask.cpython-311-darwin.so
xtcocotools/coco.py
xtcocotools/cocoeval.py
xtcocotools/mask.py
xtcocotools/version.py
xtcocotools-1.14.3.dist-info/LICENSE
xtcocotools-1.14.3.dist-info/METADATA
xtcocotools-1.14.3.dist-info/WHEEL
xtcocotools-1.14.3.dist-info/top_level.txt
xtcocotools-1.14.3.dist-info/RECORD
