Metadata-Version: 2.1
Name: xtcocotools
Version: 1.14.3
Summary: Extended COCO API
Home-page: https://github.com/jin-s13/xtcocoapi
License-File: LICENSE
